{"proj_code":{"0":"PROJ001","1":"PROJ002","2":"PROJ003","3":"PROJ004","4":"PROJ005"},"proj_name":{"0":"Big Project","1":"Little project","2":"Waterfall project","3":"Agile project","4":"R&D project"},"task_list":{"0":[["everyday task","ProdA"],["everyday task","ProdB"],["big task","ProdB"]],"1":[["everyday task","ProdA"],["small task","ProdB"],["routine tasks","General"]],"2":[["unexpected issue task","ProdA"],["special task","ProdB"]],"3":[["stand-up task","ProdA"],["sitting down","ProdB"],["bug fixing","ProdA"],["code review","ProdC"],["technical debt avoidance","ProdA"]],"4":[["where did the time go","ProdA"],["break-through celebration","ProdB"]]}}